maestror/__init__.py
maestror/enumerations.py
maestror/models.py
maestror/parsers/__init__.py
maestror/parsers/data_parser.py
maestror/parsers/run_parser.py
maestror/parsers/task_parser.py
maestror/schemas.py
maestror/servers/__init__.py
maestror/servers/control/__init__.py
maestror/servers/control/main.py
maestror/servers/control/pilot.py
maestror/servers/control/postman/__init__.py
maestror/servers/control/postman/postman.py
maestror/servers/control/postman/templates/static/css/main.css
maestror/servers/control/postman/templates/templates/base.html
maestror/servers/control/postman/templates/templates/task_notification.html
maestror/servers/control/schedule.py
maestror/servers/executor/__init__.py
maestror/servers/executor/consumer.py
maestror/servers/executor/main.py
maestror-0.1.0.dist-info/LICENSE
maestror-0.1.0.dist-info/METADATA
maestror-0.1.0.dist-info/WHEEL
maestror-0.1.0.dist-info/RECORD
