Metadata-Version: 2.1
Name: maestror
Version: 0.1.0
Summary: 
Author: jodafons
Author-email: jodafons@lps.ufrj.br
Requires-Python: >=3.9,<4.0
Classifier: Programming Language :: Python :: 3
Classifier: Programming Language :: Python :: 3.9
Classifier: Programming Language :: Python :: 3.10
Classifier: Programming Language :: Python :: 3.11
Classifier: Programming Language :: Python :: 3.12
Requires-Dist: ansi2html (>=1.8.0,<2.0.0)
Requires-Dist: benedict (>=0.3.2,<0.4.0)
Requires-Dist: charset-normalizer (>=3.3.1,<4.0.0)
Requires-Dist: cython (>=3.0.3,<4.0.0)
Requires-Dist: expand-folders (>=1.0.0,<2.0.0)
Requires-Dist: fastapi (>=0.103.2,<0.104.0)
Requires-Dist: flask-mail (>=0.9.1,<0.10.0)
Requires-Dist: flask-security (>=3.0.0,<4.0.0)
Requires-Dist: gputil (>=1.4.0,<2.0.0)
Requires-Dist: gradio (==3.41.2)
Requires-Dist: jinja2 (>=3.1.2,<4.0.0)
Requires-Dist: loguru (>=0.7.2,<0.8.0)
Requires-Dist: mlflow (>=2.8.0,<3.0.0)
Requires-Dist: netifaces (>=0.11.0,<0.12.0)
Requires-Dist: nvsmi (>=0.4.2,<0.5.0)
Requires-Dist: orjson (>=3.9.9,<4.0.0)
Requires-Dist: passlib (>=1.7.4,<2.0.0)
Requires-Dist: prettytable (>=3.9.0,<4.0.0)
Requires-Dist: psutil (>=5.9.6,<6.0.0)
Requires-Dist: psycopg2-binary (>=2.9.9,<3.0.0)
Requires-Dist: ptable (>=0.9.2,<0.10.0)
Requires-Dist: py-cpuinfo (>=9.0.0,<10.0.0)
Requires-Dist: pydantic (>=2.4.2,<3.0.0)
Requires-Dist: pytest-order (>=1.1.0,<2.0.0)
Requires-Dist: python-socketio (>=5.10.0,<6.0.0)
Requires-Dist: requests (>=2.31.0,<3.0.0)
Requires-Dist: sqlalchemy-utils (>=0.41.1,<0.42.0)
Requires-Dist: tabulate (>=0.9.0,<0.10.0)
Requires-Dist: tqdm (>=4.66.1,<5.0.0)
Requires-Dist: uvicorn (>=0.23.2,<0.24.0)
Requires-Dist: wandb (>=0.15.12,<0.16.0)
Requires-Dist: werkzeug (>=3.0.0,<4.0.0)
